{
  "generated_at": "2026-03-06T00:02:12.630464+00:00",
  "source": "legiscan",
  "total": 100,
  "bills": [
    {
      "billId": "TX-HB4535",
      "state": "TX",
      "billNumber": "HB4535",
      "title": "Relating to COVID-19 vaccine administration requirements.",
      "status": "Passed Both Chambers",
      "isActive": "Yes",
      "billType": "anti",
      "stance": "Oppose",
      "category": "vaccine-mandate",
      "level": "State",
      "impact": "High",
      "summary": "Relating to COVID-19 vaccine administration requirements.",
      "sponsor": "John McQueeney (R)",
      "lastAction": "",
      "lastActionDate": "",
      "actionCount": 0,
      "stoppedWithAction": false,
      "sourceUrl": "https://legiscan.com/TX/bill/HB4535/2025",
      "legiscan_bill_id": 2001080
    },
    {
      "billId": "TX-HCR7",
      "state": "TX",
      "billNumber": "HCR7",
      "title": "Designating September 29 as Veterans of Foreign Wars of the United States Day for a 10-year period ending in 2035.",
      "status": "Passed Both Chambers",
      "isActive": "Yes",
      "billType": "anti",
      "stance": "Oppose",
      "category": "public-health",
      "level": "State",
      "impact": "High",
      "summary": "Designating September 29 as Veterans of Foreign Wars of the United States Day for a 10-year period ending in 2035.",
      "sponsor": "Carl Tepper (R)",
      "lastAction": "",
      "lastActionDate": "",
      "actionCount": 0,
      "stoppedWithAction": false,
      "sourceUrl": "https://legiscan.com/TX/bill/HCR7/2025",
      "legiscan_bill_id": 1890556
    },
    {
      "billId": "TX-SB672",
      "state": "TX",
      "billNumber": "SB672",
      "title": "Relating to a requirement that certain hospitals submit a summary of parts of their emergency operations plans to the Health and Human Services Commission.",
      "status": "Passed Both Chambers",
      "isActive": "Yes",
      "billType": "anti",
      "stance": "Oppose",
      "category": "vaccine-mandate",
      "level": "State",
      "impact": "High",
      "summary": "Relating to a requirement that certain hospitals submit a summary of parts of their emergency operations plans to the Health and Human Services Commission.",
      "sponsor": "Bryan Hughes (R)",
      "lastAction": "",
      "lastActionDate": "",
      "actionCount": 0,
      "stoppedWithAction": false,
      "sourceUrl": "https://legiscan.com/TX/bill/SB672/2025",
      "legiscan_bill_id": 1897721
    },
    {
      "billId": "FL-S1756",
      "state": "FL",
      "billNumber": "S1756",
      "title": "Medical Freedom",
      "status": "Introduced",
      "isActive": "Yes",
      "billType": "anti",
      "stance": "Oppose",
      "category": "vaccine-exemption",
      "level": "State",
      "impact": "High",
      "summary": "Citing this act as the \"Medical Freedom Act\"; repealing a provison relating to the future repeal of the definition of the term \"messenger ribonucleic acid vaccine\"; requiring certain health care practitioners and paramedics to, before administering one or more vaccines to a minor child, provide the ",
      "sponsor": "Rules",
      "lastAction": "",
      "lastActionDate": "",
      "actionCount": 0,
      "stoppedWithAction": false,
      "sourceUrl": "https://legiscan.com/FL/bill/S1756/2026",
      "legiscan_bill_id": 2071719
    },
    {
      "billId": "CA-SB602",
      "state": "CA",
      "billNumber": "SB602",
      "title": "Veterinarians: veterinarian-client-patient relationship.",
      "status": "Passed Both Chambers",
      "isActive": "Yes",
      "billType": "anti",
      "stance": "Oppose",
      "category": "public-health",
      "level": "State",
      "impact": "High",
      "summary": "An act to amend Section 4826.7 of the Business and Professions Code, relating to veterinary medicine.",
      "sponsor": "Dave Cortese (D)",
      "lastAction": "",
      "lastActionDate": "",
      "actionCount": 0,
      "stoppedWithAction": false,
      "sourceUrl": "https://legiscan.com/CA/bill/SB602/2025",
      "legiscan_bill_id": 1978835
    },
    {
      "billId": "CA-AB2563",
      "state": "CA",
      "billNumber": "AB2563",
      "title": "Sex discrimination: scope.",
      "status": "Introduced",
      "isActive": "Yes",
      "billType": "anti",
      "stance": "Oppose",
      "category": "public-health",
      "level": "State",
      "impact": "Medium",
      "summary": "An act to add Section 14.3 to the Business and Professions Code, to amend Section 51 of, and to add Section 14.1 to, the Civil Code, to add Section 17.5 to the Code of Civil Procedure, to add Section 1207 to the Commercial Code, to add Section 12.4 to the Corporations Code, to add Section 212.4 to t",
      "sponsor": "Blanca Pacheco (D)",
      "lastAction": "",
      "lastActionDate": "",
      "actionCount": 0,
      "stoppedWithAction": false,
      "sourceUrl": "https://legiscan.com/CA/bill/AB2563/2025",
      "legiscan_bill_id": 2121640
    },
    {
      "billId": "CA-AB1003",
      "state": "CA",
      "billNumber": "AB1003",
      "title": "Public health: emergency plans and wildfire research.",
      "status": "Passed Both Chambers",
      "isActive": "Yes",
      "billType": "anti",
      "stance": "Oppose",
      "category": "public-health",
      "level": "State",
      "impact": "High",
      "summary": "An act to amend Section 8593.25 of the Government Code, and to amend Section 107250 of the Health and Safety Code, relating to public health.",
      "sponsor": "Lisa Calderon (D)",
      "lastAction": "",
      "lastActionDate": "",
      "actionCount": 0,
      "stoppedWithAction": false,
      "sourceUrl": "https://legiscan.com/CA/bill/AB1003/2025",
      "legiscan_bill_id": 1978538
    },
    {
      "billId": "OH-HB664",
      "state": "OH",
      "billNumber": "HB664",
      "title": "Regards registered veterinary technician authority",
      "status": "Introduced",
      "isActive": "Yes",
      "billType": "anti",
      "stance": "Oppose",
      "category": "public-health",
      "level": "State",
      "impact": "Medium",
      "summary": "To amend section 4741.19 of the Revised Code to establish procedures that allow a registered veterinary technician to establish a veterinarian-client-patient relationship on behalf of a veterinarian to administer vaccines and antiparasitic medication to a dog or cat.",
      "sponsor": "Tex Fischer (R)",
      "lastAction": "",
      "lastActionDate": "",
      "actionCount": 0,
      "stoppedWithAction": false,
      "sourceUrl": "https://legiscan.com/OH/bill/HB664/2025",
      "legiscan_bill_id": 2101841
    },
    {
      "billId": "OH-SR21",
      "state": "OH",
      "billNumber": "SR21",
      "title": "Urge Congress support military, veteran mental health treatment",
      "status": "Passed Both Chambers",
      "isActive": "Yes",
      "billType": "anti",
      "stance": "Oppose",
      "category": "public-health",
      "level": "State",
      "impact": "High",
      "summary": "To urge the U.S. Congress to support the provision of prompt and comprehensive mental health treatment to military personnel and veterans who are suffering from post-traumatic stress disorder and other service-related stress disorders.",
      "sponsor": "Timothy Schaffer (R)",
      "lastAction": "",
      "lastActionDate": "",
      "actionCount": 0,
      "stoppedWithAction": false,
      "sourceUrl": "https://legiscan.com/OH/bill/SR21/2025",
      "legiscan_bill_id": 1954781
    },
    {
      "billId": "NY-J01608",
      "state": "NY",
      "billNumber": "J01608",
      "title": "Memorializing Governor Kathy Hochul to proclaim June 2026, as Meningitis B Awareness Month in the State of New York",
      "status": "Passed Both Chambers",
      "isActive": "Yes",
      "billType": "anti",
      "stance": "Oppose",
      "category": "public-health",
      "level": "State",
      "impact": "High",
      "summary": "Memorializing Governor Kathy Hochul to proclaim June 2026, as Meningitis B Awareness Month in the State of New York",
      "sponsor": "Gustavo Rivera (D)",
      "lastAction": "",
      "lastActionDate": "",
      "actionCount": 0,
      "stoppedWithAction": false,
      "sourceUrl": "https://legiscan.com/NY/bill/J01608/2025",
      "legiscan_bill_id": 2119095
    },
    {
      "billId": "NY-S08496",
      "state": "NY",
      "billNumber": "S08496",
      "title": "Relates to the establishment of regulations for administering immunizations taking into consideration the recommendations of the American Academy of Pediatrics, the American Academy of Family Physicians, the American College of Obstetricians and Gynecologists, the American College of Physicians, the advisory committee on immunization practices, any interstate body established for purposes of reviewing and making recommendations regarding immunization coverage and access, or other similar nationally or internationally recognized scientific organizations.",
      "status": "In Committee",
      "isActive": "Yes",
      "billType": "anti",
      "stance": "Oppose",
      "category": "public-health",
      "level": "State",
      "impact": "High",
      "summary": "Relates to the establishment of regulations for administering immunizations taking into consideration the recommendations of the American Academy of Pediatrics, the American Academy of Family Physicians, the American College of Obstetricians and Gynecologists, the American College of Physicians, the",
      "sponsor": "Michelle Hinchey (D)",
      "lastAction": "",
      "lastActionDate": "",
      "actionCount": 0,
      "stoppedWithAction": false,
      "sourceUrl": "https://legiscan.com/NY/bill/S08496/2025",
      "legiscan_bill_id": 2043101
    },
    {
      "billId": "NY-A04765",
      "state": "NY",
      "billNumber": "A04765",
      "title": "Establishes the \"New York's Own combat veterans healthcare choice program act\" to establish tax free savings accounts to pay the healthcare costs of combat veterans on active duty during Operation Enduring Freedom or Operation Iraqi Freedom, until covered by the federal government; directs the division of military and naval affairs to establish a registry of Afghanistan and Iraq veterans.",
      "status": "Introduced",
      "isActive": "Yes",
      "billType": "anti",
      "stance": "Oppose",
      "category": "public-health",
      "level": "State",
      "impact": "Medium",
      "summary": "Establishes the \"New York's Own combat veterans healthcare choice program act\" to establish tax free savings accounts to pay the healthcare costs of combat veterans on active duty during Operation Enduring Freedom or Operation Iraqi Freedom, until covered by the federal government; directs the divis",
      "sponsor": "Brian Manktelow (R)",
      "lastAction": "",
      "lastActionDate": "",
      "actionCount": 0,
      "stoppedWithAction": false,
      "sourceUrl": "https://legiscan.com/NY/bill/A04765/2025",
      "legiscan_bill_id": 1958644
    },
    {
      "billId": "NY-S06177",
      "state": "NY",
      "billNumber": "S06177",
      "title": "Relates to establishing emergency mental health units; provides for certification of all emergency mental health units, the creation of regional emergency mental health unit councils, and a New York state emergency mental health unit council to develop minimum training standards for certified emergency mental health units and minimum equipment and communication standards for emergency mental health units.",
      "status": "Introduced",
      "isActive": "Yes",
      "billType": "anti",
      "stance": "Oppose",
      "category": "public-health",
      "level": "State",
      "impact": "Medium",
      "summary": "Relates to establishing emergency mental health units; provides for certification of all emergency mental health units, the creation of regional emergency mental health unit councils, and a New York state emergency mental health unit council to develop minimum training standards for certified emerge",
      "sponsor": "Kevin Parker (D)",
      "lastAction": "",
      "lastActionDate": "",
      "actionCount": 0,
      "stoppedWithAction": false,
      "sourceUrl": "https://legiscan.com/NY/bill/S06177/2025",
      "legiscan_bill_id": 1993429
    },
    {
      "billId": "CO-SB032",
      "state": "CO",
      "billNumber": "SB032",
      "title": "Promoting Immunization Access",
      "status": "In Committee",
      "isActive": "Yes",
      "billType": "anti",
      "stance": "Oppose",
      "category": "public-health",
      "level": "State",
      "impact": "High",
      "summary": "Concerning the promotion of immunization access.",
      "sponsor": "Lindsey Daugherty (D)",
      "lastAction": "",
      "lastActionDate": "",
      "actionCount": 0,
      "stoppedWithAction": false,
      "sourceUrl": "https://legiscan.com/CO/bill/SB032/2026",
      "legiscan_bill_id": 2093866
    },
    {
      "billId": "CO-HJR1006",
      "state": "CO",
      "billNumber": "HJR1006",
      "title": "Latina & Latino Veterans",
      "status": "Passed Both Chambers",
      "isActive": "Yes",
      "billType": "anti",
      "stance": "Oppose",
      "category": "public-health",
      "level": "State",
      "impact": "High",
      "summary": "Concerning recognition of the contributions of Latina and Latino veterans.",
      "sponsor": "Carlos Barron (R)",
      "lastAction": "",
      "lastActionDate": "",
      "actionCount": 0,
      "stoppedWithAction": false,
      "sourceUrl": "https://legiscan.com/CO/bill/HJR1006/2026",
      "legiscan_bill_id": 2110618
    },
    {
      "billId": "CO-HB1238",
      "state": "CO",
      "billNumber": "HB1238",
      "title": "Designating Emergency Medical Services Essential Services",
      "status": "Introduced",
      "isActive": "Yes",
      "billType": "anti",
      "stance": "Oppose",
      "category": "public-health",
      "level": "State",
      "impact": "Medium",
      "summary": "Concerning emergency medical services provided in the state, and, in connection therewith, designating emergency medical services, including ambulance services and air ambulance services, to be essential services.",
      "sponsor": "Dusty Johnson (R)",
      "lastAction": "",
      "lastActionDate": "",
      "actionCount": 0,
      "stoppedWithAction": false,
      "sourceUrl": "https://legiscan.com/CO/bill/HB1238/2026",
      "legiscan_bill_id": 2119878
    },
    {
      "billId": "WA-HB2242",
      "state": "WA",
      "billNumber": "HB2242",
      "title": "Preserving access to preventive services by clarifying state authority and definitions.",
      "status": "Passed One Chamber",
      "isActive": "Yes",
      "billType": "anti",
      "stance": "Oppose",
      "category": "public-health",
      "level": "State",
      "impact": "High",
      "summary": "Preserving access to preventive services by clarifying state authority and definitions.",
      "sponsor": "Dan Bronoske (D)",
      "lastAction": "",
      "lastActionDate": "",
      "actionCount": 0,
      "stoppedWithAction": false,
      "sourceUrl": "https://legiscan.com/WA/bill/HB2242/2025",
      "legiscan_bill_id": 2064925
    },
    {
      "billId": "WA-SB6182",
      "state": "WA",
      "billNumber": "SB6182",
      "title": "Establishing an abortion savings program.",
      "status": "In Committee",
      "isActive": "Yes",
      "billType": "anti",
      "stance": "Oppose",
      "category": "public-health",
      "level": "State",
      "impact": "High",
      "summary": "Establishing an abortion savings program.",
      "sponsor": "Jessica Bateman (D)",
      "lastAction": "",
      "lastActionDate": "",
      "actionCount": 0,
      "stoppedWithAction": false,
      "sourceUrl": "https://legiscan.com/WA/bill/SB6182/2025",
      "legiscan_bill_id": 2082711
    },
    {
      "billId": "WA-HB2266",
      "state": "WA",
      "billNumber": "HB2266",
      "title": "Encouraging permanent supportive housing, transitional housing, indoor emergency housing, and indoor emergency shelters.",
      "status": "In Committee",
      "isActive": "Yes",
      "billType": "anti",
      "stance": "Oppose",
      "category": "public-health",
      "level": "State",
      "impact": "High",
      "summary": "Encouraging permanent supportive housing, transitional housing, indoor emergency housing, and indoor emergency shelters.",
      "sponsor": "Strom Peterson (D)",
      "lastAction": "",
      "lastActionDate": "",
      "actionCount": 0,
      "stoppedWithAction": false,
      "sourceUrl": "https://legiscan.com/WA/bill/HB2266/2025",
      "legiscan_bill_id": 2065885
    },
    {
      "billId": "ID-S1346",
      "state": "ID",
      "billNumber": "S1346",
      "title": "Adds to existing law to establish a moratorium on certain uses of human gene therapy products.",
      "status": "Introduced",
      "isActive": "Yes",
      "billType": "anti",
      "stance": "Oppose",
      "category": "public-health",
      "level": "State",
      "impact": "Medium",
      "summary": "IMMUNIZATIONS -- Adds to existing law to establish a moratorium on certain uses of human gene therapy products.",
      "sponsor": "Judiciary and Rules Committee",
      "lastAction": "",
      "lastActionDate": "",
      "actionCount": 0,
      "stoppedWithAction": false,
      "sourceUrl": "https://legiscan.com/ID/bill/S1346/2026",
      "legiscan_bill_id": 2125440
    },
    {
      "billId": "ID-H0724",
      "state": "ID",
      "billNumber": "H0724",
      "title": "Adds to existing law to provide for a notice of safety-related rights for foster children.",
      "status": "Introduced",
      "isActive": "Yes",
      "billType": "anti",
      "stance": "Oppose",
      "category": "public-health",
      "level": "State",
      "impact": "Medium",
      "summary": "CHILD CARE LICENSING -- Adds to existing law to provide for a notice of safety-related rights for foster children.",
      "sponsor": "Health and Welfare Committee",
      "lastAction": "",
      "lastActionDate": "",
      "actionCount": 0,
      "stoppedWithAction": false,
      "sourceUrl": "https://legiscan.com/ID/bill/H0724/2026",
      "legiscan_bill_id": 2119139
    },
    {
      "billId": "ID-S1271",
      "state": "ID",
      "billNumber": "S1271",
      "title": "Adds to existing law to declare certain rats a public health and safety nuisance and to require abatement.",
      "status": "Introduced",
      "isActive": "Yes",
      "billType": "anti",
      "stance": "Oppose",
      "category": "vaccine-mandate",
      "level": "State",
      "impact": "Medium",
      "summary": "RATS -- Adds to existing law to declare certain rats a public health and safety nuisance and to require abatement.",
      "sponsor": "Agricultural Affairs Committee",
      "lastAction": "",
      "lastActionDate": "",
      "actionCount": 0,
      "stoppedWithAction": false,
      "sourceUrl": "https://legiscan.com/ID/bill/S1271/2026",
      "legiscan_bill_id": 2113203
    },
    {
      "billId": "MO-HB1976",
      "state": "MO",
      "billNumber": "HB1976",
      "title": "Modifies provisions relating to the ordering and administration of vaccines by pharmacists",
      "status": "Introduced",
      "isActive": "Yes",
      "billType": "anti",
      "stance": "Oppose",
      "category": "public-health",
      "level": "State",
      "impact": "Medium",
      "summary": "Modifies provisions relating to the ordering and administration of vaccines by pharmacists",
      "sponsor": "Bennie Cook (R)",
      "lastAction": "",
      "lastActionDate": "",
      "actionCount": 0,
      "stoppedWithAction": false,
      "sourceUrl": "https://legiscan.com/MO/bill/HB1976/2026",
      "legiscan_bill_id": 2054996
    },
    {
      "billId": "MO-SB916",
      "state": "MO",
      "billNumber": "SB916",
      "title": "Modifies provisions relating to sovereign immunity",
      "status": "Introduced",
      "isActive": "Yes",
      "billType": "anti",
      "stance": "Oppose",
      "category": "public-health",
      "level": "State",
      "impact": "Medium",
      "summary": "Modifies provisions relating to sovereign immunity",
      "sponsor": "Jamie Burger (R)",
      "lastAction": "",
      "lastActionDate": "",
      "actionCount": 0,
      "stoppedWithAction": false,
      "sourceUrl": "https://legiscan.com/MO/bill/SB916/2026",
      "legiscan_bill_id": 2055529
    },
    {
      "billId": "MO-SB974",
      "state": "MO",
      "billNumber": "SB974",
      "title": "Modifies provisions relating to compensation for services rendered in veteran benefits matters",
      "status": "In Committee",
      "isActive": "Yes",
      "billType": "anti",
      "stance": "Oppose",
      "category": "vaccine-liability",
      "level": "State",
      "impact": "High",
      "summary": "Modifies provisions relating to compensation for services rendered in veteran benefits matters",
      "sponsor": "Rusty Black (R)",
      "lastAction": "",
      "lastActionDate": "",
      "actionCount": 0,
      "stoppedWithAction": false,
      "sourceUrl": "https://legiscan.com/MO/bill/SB974/2026",
      "legiscan_bill_id": 2055944
    },
    {
      "billId": "GA-HR1476",
      "state": "GA",
      "billNumber": "HR1476",
      "title": "National Immunization Awareness Month; August; recognize",
      "status": "Introduced",
      "isActive": "Yes",
      "billType": "anti",
      "stance": "Oppose",
      "category": "public-health",
      "level": "State",
      "impact": "Medium",
      "summary": "A RESOLUTION recognizing August as National Immunization Awareness Month; and for other purposes.",
      "sponsor": "Sharon Cooper (R)",
      "lastAction": "",
      "lastActionDate": "",
      "actionCount": 0,
      "stoppedWithAction": false,
      "sourceUrl": "https://legiscan.com/GA/bill/HR1476/2025",
      "legiscan_bill_id": 2124858
    },
    {
      "billId": "GA-HB531",
      "state": "GA",
      "billNumber": "HB531",
      "title": "Appeal and error; certain appellate procedures regarding the denial of sovereign and any other immunity available to the state or a city or county in this state; provide",
      "status": "In Committee",
      "isActive": "Yes",
      "billType": "anti",
      "stance": "Oppose",
      "category": "public-health",
      "level": "State",
      "impact": "High",
      "summary": "A BILL to be entitled an Act to amend Code Section 5-6-34 of the Official Code of Georgia Annotated, relating to judgments and rulings deemed directly appealable, procedure for review of judgments, orders, or decisions not subject to direct appeal, scope of review, hearings in criminal cases involvi",
      "sponsor": "Matt Reeves (R)",
      "lastAction": "",
      "lastActionDate": "",
      "actionCount": 0,
      "stoppedWithAction": false,
      "sourceUrl": "https://legiscan.com/GA/bill/HB531/2025",
      "legiscan_bill_id": 1976315
    },
    {
      "billId": "GA-SR84",
      "state": "GA",
      "billNumber": "SR84",
      "title": "Right to Reproductive Freedom; provide",
      "status": "Introduced",
      "isActive": "Yes",
      "billType": "anti",
      "stance": "Oppose",
      "category": "public-health",
      "level": "State",
      "impact": "Medium",
      "summary": "A RESOLUTION proposing an amendment to the Constitution so as to provide that every individual has a fundamental right to reproductive freedom and such right shall not be denied, burdened, or infringed upon unless justified by a compelling state interest; to limit the purpose of a compelling state i",
      "sponsor": "Sally Harrell (D)",
      "lastAction": "",
      "lastActionDate": "",
      "actionCount": 0,
      "stoppedWithAction": false,
      "sourceUrl": "https://legiscan.com/GA/bill/SR84/2025",
      "legiscan_bill_id": 1949609
    },
    {
      "billId": "PA-SB1018",
      "state": "PA",
      "billNumber": "SB1018",
      "title": "Providing for voluntary mRNA vaccine requirement, for waivers and informed consent, for employer and entity penalties, for Pennsylvania National Guard requirements and for enforcement; and imposing penalties.",
      "status": "Introduced",
      "isActive": "Yes",
      "billType": "anti",
      "stance": "Oppose",
      "category": "vaccine-mandate",
      "level": "State",
      "impact": "Medium",
      "summary": "An Act providing for voluntary mRNA vaccine requirement, for waivers and informed consent, for employer and entity penalties, for Pennsylvania National Guard requirements and for enforcement; and imposing penalties.",
      "sponsor": "Doug Mastriano (R)",
      "lastAction": "",
      "lastActionDate": "",
      "actionCount": 0,
      "stoppedWithAction": false,
      "sourceUrl": "https://legiscan.com/PA/bill/SB1018/2025",
      "legiscan_bill_id": 2047054
    },
    {
      "billId": "PA-HR413",
      "state": "PA",
      "billNumber": "HR413",
      "title": "Recognizing \"Black History Month\" in Pennsylvania by commemorating the recently passed 50th anniversary of the closure of Freedom House Ambulance Service.",
      "status": "Passed Both Chambers",
      "isActive": "Yes",
      "billType": "anti",
      "stance": "Oppose",
      "category": "public-health",
      "level": "State",
      "impact": "High",
      "summary": "A Resolution recognizing \"Black History Month\" in Pennsylvania by commemorating the recently passed 50th anniversary of the closure of Freedom House Ambulance Service.",
      "sponsor": "Aerion Abney (D)",
      "lastAction": "",
      "lastActionDate": "",
      "actionCount": 0,
      "stoppedWithAction": false,
      "sourceUrl": "https://legiscan.com/PA/bill/HR413/2025",
      "legiscan_bill_id": 2103327
    },
    {
      "billId": "PA-HB1491",
      "state": "PA",
      "billNumber": "HB1491",
      "title": "In emergency medical services system, further providing for declaration of policy, for definitions, for emergency medical services system programs and for duties of department; establishing the State EMS Advisory Board; and further providing for emergency medical services patient care reports, for funding, for notification of trauma center closure, for State Advisory Board, for regional emergency medical services councils, for comprehensive plan, for contracts and grants and for scholarships for recruitment, training and retention.",
      "status": "Introduced",
      "isActive": "Yes",
      "billType": "anti",
      "stance": "Oppose",
      "category": "public-health",
      "level": "State",
      "impact": "Medium",
      "summary": "An Act amending Title 35 (Health and Safety) of the Pennsylvania Consolidated Statutes, in emergency medical services system, further providing for declaration of policy, for definitions, for emergency medical services system programs and for duties of department; establishing the State EMS Advisory",
      "sponsor": "Martin Causer (R)",
      "lastAction": "",
      "lastActionDate": "",
      "actionCount": 0,
      "stoppedWithAction": false,
      "sourceUrl": "https://legiscan.com/PA/bill/HB1491/2025",
      "legiscan_bill_id": 2032411
    },
    {
      "billId": "MA-H3072",
      "state": "MA",
      "billNumber": "H3072",
      "title": "For an enabling authority - Vaccination Tax Credit",
      "status": "Introduced",
      "isActive": "Yes",
      "billType": "anti",
      "stance": "Oppose",
      "category": "public-health",
      "level": "State",
      "impact": "Medium",
      "summary": "Relative to providing certain individuals with a vaccination tax credit. Revenue.",
      "sponsor": "Michael Day (D)",
      "lastAction": "",
      "lastActionDate": "",
      "actionCount": 0,
      "stoppedWithAction": false,
      "sourceUrl": "https://legiscan.com/MA/bill/H3072/2025",
      "legiscan_bill_id": 2001480
    },
    {
      "billId": "MA-H3070",
      "state": "MA",
      "billNumber": "H3070",
      "title": "For a COVID-19 vaccination tax credit",
      "status": "Introduced",
      "isActive": "Yes",
      "billType": "anti",
      "stance": "Oppose",
      "category": "public-health",
      "level": "State",
      "impact": "Medium",
      "summary": "Relative to a COVID-19 vaccination tax credit. Revenue.",
      "sponsor": "Michael Day (D)",
      "lastAction": "",
      "lastActionDate": "",
      "actionCount": 0,
      "stoppedWithAction": false,
      "sourceUrl": "https://legiscan.com/MA/bill/H3070/2025",
      "legiscan_bill_id": 2001611
    },
    {
      "billId": "MA-H4118",
      "state": "MA",
      "billNumber": "H4118",
      "title": "To establish an emergency medical services treatment-in-place (TIP) pilot program",
      "status": "Introduced",
      "isActive": "Yes",
      "billType": "anti",
      "stance": "Oppose",
      "category": "public-health",
      "level": "State",
      "impact": "Medium",
      "summary": "For legislation to establish an emergency medical services treatment-in-place pilot program. Public Health.",
      "sponsor": "Leigh Davis (D)",
      "lastAction": "",
      "lastActionDate": "",
      "actionCount": 0,
      "stoppedWithAction": false,
      "sourceUrl": "https://legiscan.com/MA/bill/H4118/2025",
      "legiscan_bill_id": 2030423
    },
    {
      "billId": "TX-HB3540",
      "state": "TX",
      "billNumber": "HB3540",
      "title": "Relating to the regulation of pharmacists and the practice of pharmacy, including the administration of a medication and the ordering and administration of an immunization or vaccination by a pharmacist.",
      "status": "In Committee",
      "isActive": "Yes",
      "billType": "anti",
      "stance": "Oppose",
      "category": "public-health",
      "level": "State",
      "impact": "High",
      "summary": "Relating to the regulation of pharmacists and the practice of pharmacy, including the administration of a medication and the ordering and administration of an immunization or vaccination by a pharmacist.",
      "sponsor": "Sam Harless (R)",
      "lastAction": "",
      "lastActionDate": "",
      "actionCount": 0,
      "stoppedWithAction": false,
      "sourceUrl": "https://legiscan.com/TX/bill/HB3540/2025",
      "legiscan_bill_id": 1988741
    },
    {
      "billId": "TX-HB3441",
      "state": "TX",
      "billNumber": "HB3441",
      "title": "Relating to the liability of vaccine manufacturers that advertise a harmful vaccine.",
      "status": "Passed Both Chambers",
      "isActive": "Yes",
      "billType": "anti",
      "stance": "Oppose",
      "category": "vaccine-liability",
      "level": "State",
      "impact": "High",
      "summary": "Relating to the liability of vaccine manufacturers that advertise a harmful vaccine.",
      "sponsor": "Shelley Luther (R)",
      "lastAction": "",
      "lastActionDate": "",
      "actionCount": 0,
      "stoppedWithAction": false,
      "sourceUrl": "https://legiscan.com/TX/bill/HB3441/2025",
      "legiscan_bill_id": 1985653
    },
    {
      "billId": "TX-HB4076",
      "state": "TX",
      "billNumber": "HB4076",
      "title": "Relating to prohibiting organ transplant recipient discrimination on the basis of vaccination status.",
      "status": "Passed Both Chambers",
      "isActive": "Yes",
      "billType": "anti",
      "stance": "Oppose",
      "category": "public-health",
      "level": "State",
      "impact": "High",
      "summary": "Relating to prohibiting organ transplant recipient discrimination on the basis of vaccination status.",
      "sponsor": "Jeff Leach (R)",
      "lastAction": "",
      "lastActionDate": "",
      "actionCount": 0,
      "stoppedWithAction": false,
      "sourceUrl": "https://legiscan.com/TX/bill/HB4076/2025",
      "legiscan_bill_id": 1995074
    },
    {
      "billId": "TX-SB254",
      "state": "TX",
      "billNumber": "SB254",
      "title": "Relating to the administration of a medication and the ordering and administration of an immunization or vaccination by a pharmacist.",
      "status": "Introduced",
      "isActive": "Yes",
      "billType": "anti",
      "stance": "Oppose",
      "category": "public-health",
      "level": "State",
      "impact": "Medium",
      "summary": "Relating to the administration of a medication and the ordering and administration of an immunization or vaccination by a pharmacist.",
      "sponsor": "Peter Flores (R)",
      "lastAction": "",
      "lastActionDate": "",
      "actionCount": 0,
      "stoppedWithAction": false,
      "sourceUrl": "https://legiscan.com/TX/bill/SB254/2025",
      "legiscan_bill_id": 1890311
    },
    {
      "billId": "TX-HB943",
      "state": "TX",
      "billNumber": "HB943",
      "title": "Relating to informed consent before the provision of certain medical treatments involving COVID-19 vaccination.",
      "status": "Introduced",
      "isActive": "Yes",
      "billType": "anti",
      "stance": "Oppose",
      "category": "informed-consent",
      "level": "State",
      "impact": "Medium",
      "summary": "Relating to informed consent before the provision of certain medical treatments involving COVID-19 vaccination.",
      "sponsor": "Briscoe Cain (R)",
      "lastAction": "",
      "lastActionDate": "",
      "actionCount": 0,
      "stoppedWithAction": false,
      "sourceUrl": "https://legiscan.com/TX/bill/HB943/2025",
      "legiscan_bill_id": 1891680
    },
    {
      "billId": "TX-SB96",
      "state": "TX",
      "billNumber": "SB96",
      "title": "Relating to vaccine administration requirements and protection of immunization exemptions for health reasons.",
      "status": "Introduced",
      "isActive": "Yes",
      "billType": "anti",
      "stance": "Oppose",
      "category": "vaccine-exemption",
      "level": "State",
      "impact": "Medium",
      "summary": "Relating to vaccine administration requirements and protection of immunization exemptions for health reasons.",
      "sponsor": "Bob Hall (R)",
      "lastAction": "",
      "lastActionDate": "",
      "actionCount": 0,
      "stoppedWithAction": false,
      "sourceUrl": "https://legiscan.com/TX/bill/SB96/2025",
      "legiscan_bill_id": 1891133
    },
    {
      "billId": "TX-HB3304",
      "state": "TX",
      "billNumber": "HB3304",
      "title": "Relating to a prohibition on vaccination mandates.",
      "status": "Introduced",
      "isActive": "Yes",
      "billType": "anti",
      "stance": "Oppose",
      "category": "vaccine-mandate",
      "level": "State",
      "impact": "High",
      "summary": "Relating to a prohibition on vaccination mandates.",
      "sponsor": "David Lowe (R)",
      "lastAction": "",
      "lastActionDate": "",
      "actionCount": 0,
      "stoppedWithAction": false,
      "sourceUrl": "https://legiscan.com/TX/bill/HB3304/2025",
      "legiscan_bill_id": 1983139
    },
    {
      "billId": "TX-SR72",
      "state": "TX",
      "billNumber": "SR72",
      "title": "Recognizing Texans for Vaccine Choice on the occasion of its 10th anniversary of its founding.",
      "status": "Passed Both Chambers",
      "isActive": "Yes",
      "billType": "anti",
      "stance": "Oppose",
      "category": "public-health",
      "level": "State",
      "impact": "High",
      "summary": "Recognizing Texans for Vaccine Choice on the occasion of its 10th anniversary of its founding.",
      "sponsor": "Mayes Middleton (R)",
      "lastAction": "",
      "lastActionDate": "",
      "actionCount": 0,
      "stoppedWithAction": false,
      "sourceUrl": "https://legiscan.com/TX/bill/SR72/2025",
      "legiscan_bill_id": 1963416
    },
    {
      "billId": "TX-SB95",
      "state": "TX",
      "billNumber": "SB95",
      "title": "Relating to the administration of immunizations to children, including required written informed consent to those immunizations and civil liability for failure to obtain the consent; providing an administrative penalty.",
      "status": "In Committee",
      "isActive": "Yes",
      "billType": "anti",
      "stance": "Oppose",
      "category": "vaccine-mandate",
      "level": "State",
      "impact": "High",
      "summary": "Relating to the administration of immunizations to children, including required written informed consent to those immunizations and civil liability for failure to obtain the consent; providing an administrative penalty.",
      "sponsor": "Bob Hall (R)",
      "lastAction": "",
      "lastActionDate": "",
      "actionCount": 0,
      "stoppedWithAction": false,
      "sourceUrl": "https://legiscan.com/TX/bill/SB95/2025",
      "legiscan_bill_id": 1890940
    },
    {
      "billId": "TX-HCR94",
      "state": "TX",
      "billNumber": "HCR94",
      "title": "Designating May 8 as Vaccination Day for a 10-year period ending in 2035.",
      "status": "Introduced",
      "isActive": "Yes",
      "billType": "anti",
      "stance": "Oppose",
      "category": "public-health",
      "level": "State",
      "impact": "Medium",
      "summary": "Designating May 8 as Vaccination Day for a 10-year period ending in 2035.",
      "sponsor": "Christina Morales (D)",
      "lastAction": "",
      "lastActionDate": "",
      "actionCount": 0,
      "stoppedWithAction": false,
      "sourceUrl": "https://legiscan.com/TX/bill/HCR94/2025",
      "legiscan_bill_id": 1990723
    },
    {
      "billId": "TX-SB269",
      "state": "TX",
      "billNumber": "SB269",
      "title": "Relating to required reports of certain vaccine-related or drug-related adverse events.",
      "status": "Passed Both Chambers",
      "isActive": "Yes",
      "billType": "anti",
      "stance": "Oppose",
      "category": "vaccine-mandate",
      "level": "State",
      "impact": "High",
      "summary": "Relating to required reports of certain vaccine-related or drug-related adverse events.",
      "sponsor": "Charles Perry (R)",
      "lastAction": "",
      "lastActionDate": "",
      "actionCount": 0,
      "stoppedWithAction": false,
      "sourceUrl": "https://legiscan.com/TX/bill/SB269/2025",
      "legiscan_bill_id": 1890563
    },
    {
      "billId": "TX-SB119",
      "state": "TX",
      "billNumber": "SB119",
      "title": "Relating to required labeling of food containing mRNA vaccine material.",
      "status": "Introduced",
      "isActive": "Yes",
      "billType": "anti",
      "stance": "Oppose",
      "category": "vaccine-mandate",
      "level": "State",
      "impact": "Medium",
      "summary": "Relating to required labeling of food containing mRNA vaccine material.",
      "sponsor": "Bob Hall (R)",
      "lastAction": "",
      "lastActionDate": "",
      "actionCount": 0,
      "stoppedWithAction": false,
      "sourceUrl": "https://legiscan.com/TX/bill/SB119/2025",
      "legiscan_bill_id": 1890378
    },
    {
      "billId": "TX-HCR105",
      "state": "TX",
      "billNumber": "HCR105",
      "title": "Designating June 3 as Vaccine Injury Awareness Day for a 10-year period ending in 2035.",
      "status": "Introduced",
      "isActive": "Yes",
      "billType": "anti",
      "stance": "Oppose",
      "category": "vaccine-liability",
      "level": "State",
      "impact": "Medium",
      "summary": "Designating June 3 as Vaccine Injury Awareness Day for a 10-year period ending in 2035.",
      "sponsor": "Steve Toth (R)",
      "lastAction": "",
      "lastActionDate": "",
      "actionCount": 0,
      "stoppedWithAction": false,
      "sourceUrl": "https://legiscan.com/TX/bill/HCR105/2025",
      "legiscan_bill_id": 1999943
    },
    {
      "billId": "TX-HB4687",
      "state": "TX",
      "billNumber": "HB4687",
      "title": "Relating to the applicability of certain immunity and liability laws to certain charter school campuses or programs.",
      "status": "Passed Both Chambers",
      "isActive": "Yes",
      "billType": "anti",
      "stance": "Oppose",
      "category": "vaccine-liability",
      "level": "State",
      "impact": "High",
      "summary": "Relating to the applicability of certain immunity and liability laws to certain charter school campuses or programs.",
      "sponsor": "Barbara Gervin-Hawkins (D)",
      "lastAction": "",
      "lastActionDate": "",
      "actionCount": 0,
      "stoppedWithAction": false,
      "sourceUrl": "https://legiscan.com/TX/bill/HB4687/2025",
      "legiscan_bill_id": 2005398
    },
    {
      "billId": "TX-HB772",
      "state": "TX",
      "billNumber": "HB772",
      "title": "Relating to the immunization data included in and excluded from the immunization registry.",
      "status": "Introduced",
      "isActive": "Yes",
      "billType": "pro",
      "stance": "Support",
      "category": "public-health",
      "level": "State",
      "impact": "Medium",
      "summary": "Relating to the immunization data included in and excluded from the immunization registry.",
      "sponsor": "Donna Howard (D)",
      "lastAction": "",
      "lastActionDate": "",
      "actionCount": 0,
      "stoppedWithAction": false,
      "sourceUrl": "https://legiscan.com/TX/bill/HB772/2025",
      "legiscan_bill_id": 1890924
    },
    {
      "billId": "TX-SB46",
      "state": "TX",
      "billNumber": "SB46",
      "title": "Relating to the immunization data included in and excluded from the immunization registry.",
      "status": "Introduced",
      "isActive": "Yes",
      "billType": "pro",
      "stance": "Support",
      "category": "public-health",
      "level": "State",
      "impact": "Medium",
      "summary": "Relating to the immunization data included in and excluded from the immunization registry.",
      "sponsor": "Judith Zaffirini (D)",
      "lastAction": "",
      "lastActionDate": "",
      "actionCount": 0,
      "stoppedWithAction": false,
      "sourceUrl": "https://legiscan.com/TX/bill/SB46/2025",
      "legiscan_bill_id": 1891325
    },
    {
      "billId": "TX-SB842",
      "state": "TX",
      "billNumber": "SB842",
      "title": "Relating to immunity for ringside physicians assigned to combative sports events.",
      "status": "Passed Both Chambers",
      "isActive": "Yes",
      "billType": "anti",
      "stance": "Oppose",
      "category": "public-health",
      "level": "State",
      "impact": "High",
      "summary": "Relating to immunity for ringside physicians assigned to combative sports events.",
      "sponsor": "Charles Schwertner (R)",
      "lastAction": "",
      "lastActionDate": "",
      "actionCount": 0,
      "stoppedWithAction": false,
      "sourceUrl": "https://legiscan.com/TX/bill/SB842/2025",
      "legiscan_bill_id": 1928280
    },
    {
      "billId": "TX-HB1586",
      "state": "TX",
      "billNumber": "HB1586",
      "title": "Relating to an exemption from required immunizations for school enrollment.",
      "status": "Passed Both Chambers",
      "isActive": "Yes",
      "billType": "anti",
      "stance": "Oppose",
      "category": "vaccine-exemption",
      "level": "State",
      "impact": "High",
      "summary": "Relating to an exemption from required immunizations for school enrollment.",
      "sponsor": "Lacey Hull (R)",
      "lastAction": "",
      "lastActionDate": "",
      "actionCount": 0,
      "stoppedWithAction": false,
      "sourceUrl": "https://legiscan.com/TX/bill/HB1586/2025",
      "legiscan_bill_id": 1895991
    },
    {
      "billId": "TX-SB2119",
      "state": "TX",
      "billNumber": "SB2119",
      "title": "Relating to an exemption from certain immunization requirements for medical and veterinary students.",
      "status": "In Committee",
      "isActive": "Yes",
      "billType": "anti",
      "stance": "Oppose",
      "category": "vaccine-exemption",
      "level": "State",
      "impact": "High",
      "summary": "Relating to an exemption from certain immunization requirements for medical and veterinary students.",
      "sponsor": "Kevin Sparks (R)",
      "lastAction": "",
      "lastActionDate": "",
      "actionCount": 0,
      "stoppedWithAction": false,
      "sourceUrl": "https://legiscan.com/TX/bill/SB2119/2025",
      "legiscan_bill_id": 1996169
    },
    {
      "billId": "TX-SB1874",
      "state": "TX",
      "billNumber": "SB1874",
      "title": "Relating to immunity from certain disciplinary proceedings against a professional employee of a school district for certain actions concerning public school discipline and law and order.",
      "status": "In Committee",
      "isActive": "Yes",
      "billType": "anti",
      "stance": "Oppose",
      "category": "public-health",
      "level": "State",
      "impact": "High",
      "summary": "Relating to immunity from certain disciplinary proceedings against a professional employee of a school district for certain actions concerning public school discipline and law and order.",
      "sponsor": "Charles Perry (R)",
      "lastAction": "",
      "lastActionDate": "",
      "actionCount": 0,
      "stoppedWithAction": false,
      "sourceUrl": "https://legiscan.com/TX/bill/SB1874/2025",
      "legiscan_bill_id": 1991376
    },
    {
      "billId": "TX-SB240",
      "state": "TX",
      "billNumber": "SB240",
      "title": "Relating to the designation and use of certain spaces and facilities according to biological sex; authorizing a civil penalty and a private civil right of action.",
      "status": "In Committee",
      "isActive": "Yes",
      "billType": "anti",
      "stance": "Oppose",
      "category": "public-health",
      "level": "State",
      "impact": "High",
      "summary": "Relating to the designation and use of certain spaces and facilities according to biological sex; authorizing a civil penalty and a private civil right of action.",
      "sponsor": "Mayes Middleton (R)",
      "lastAction": "",
      "lastActionDate": "",
      "actionCount": 0,
      "stoppedWithAction": false,
      "sourceUrl": "https://legiscan.com/TX/bill/SB240/2025",
      "legiscan_bill_id": 1890533
    },
    {
      "billId": "TX-SB2574",
      "state": "TX",
      "billNumber": "SB2574",
      "title": "Relating to preserving religious liberty from nativist jurisprudence.",
      "status": "Introduced",
      "isActive": "Yes",
      "billType": "anti",
      "stance": "Oppose",
      "category": "public-health",
      "level": "State",
      "impact": "Medium",
      "summary": "Relating to preserving religious liberty from nativist jurisprudence.",
      "sponsor": "Mayes Middleton (R)",
      "lastAction": "",
      "lastActionDate": "",
      "actionCount": 0,
      "stoppedWithAction": false,
      "sourceUrl": "https://legiscan.com/TX/bill/SB2574/2025",
      "legiscan_bill_id": 2006412
    },
    {
      "billId": "TX-HB33",
      "state": "TX",
      "billNumber": "HB33",
      "title": "Relating to active shooter incidents at primary and secondary school facilities and other emergencies.",
      "status": "Passed Both Chambers",
      "isActive": "Yes",
      "billType": "anti",
      "stance": "Oppose",
      "category": "public-health",
      "level": "State",
      "impact": "High",
      "summary": "Relating to active shooter incidents at primary and secondary school facilities and other emergencies.",
      "sponsor": "Don McLaughlin (R)",
      "lastAction": "",
      "lastActionDate": "",
      "actionCount": 0,
      "stoppedWithAction": false,
      "sourceUrl": "https://legiscan.com/TX/bill/HB33/2025",
      "legiscan_bill_id": 1990287
    },
    {
      "billId": "TX-HB742",
      "state": "TX",
      "billNumber": "HB742",
      "title": "Relating to human trafficking prevention, including training for first responders, disclosure of human trafficking information by certain health care facilities, and protection for facility employees who report human trafficking.",
      "status": "Passed Both Chambers",
      "isActive": "Yes",
      "billType": "anti",
      "stance": "Oppose",
      "category": "public-health",
      "level": "State",
      "impact": "High",
      "summary": "Relating to human trafficking prevention, including training for first responders, disclosure of human trafficking information by certain health care facilities, and protection for facility employees who report human trafficking.",
      "sponsor": "Senfronia Thompson (D)",
      "lastAction": "",
      "lastActionDate": "",
      "actionCount": 0,
      "stoppedWithAction": false,
      "sourceUrl": "https://legiscan.com/TX/bill/HB742/2025",
      "legiscan_bill_id": 1891506
    },
    {
      "billId": "TX-SB2862",
      "state": "TX",
      "billNumber": "SB2862",
      "title": "Relating to active shooter events and other emergencies, including certain accreditations of law enforcement agencies that respond to such emergencies.",
      "status": "Introduced",
      "isActive": "Yes",
      "billType": "anti",
      "stance": "Oppose",
      "category": "public-health",
      "level": "State",
      "impact": "Medium",
      "summary": "Relating to active shooter events and other emergencies, including certain accreditations of law enforcement agencies that respond to such emergencies.",
      "sponsor": "Peter Flores (R)",
      "lastAction": "",
      "lastActionDate": "",
      "actionCount": 0,
      "stoppedWithAction": false,
      "sourceUrl": "https://legiscan.com/TX/bill/SB2862/2025",
      "legiscan_bill_id": 2008027
    },
    {
      "billId": "TX-HB964",
      "state": "TX",
      "billNumber": "HB964",
      "title": "Relating to the regulation of laboratory developed tests during a federally declared public health emergency.",
      "status": "Introduced",
      "isActive": "Yes",
      "billType": "anti",
      "stance": "Oppose",
      "category": "public-health",
      "level": "State",
      "impact": "Medium",
      "summary": "Relating to the regulation of laboratory developed tests during a federally declared public health emergency.",
      "sponsor": "Brian Harrison (R)",
      "lastAction": "",
      "lastActionDate": "",
      "actionCount": 0,
      "stoppedWithAction": false,
      "sourceUrl": "https://legiscan.com/TX/bill/HB964/2025",
      "legiscan_bill_id": 1890607
    },
    {
      "billId": "TX-SB1980",
      "state": "TX",
      "billNumber": "SB1980",
      "title": "Relating to increasing the criminal penalty for the offense of assault committed against certain public servants and to the prosecution of the criminal offense of interference with public duties of those public servants.",
      "status": "In Committee",
      "isActive": "Yes",
      "billType": "anti",
      "stance": "Oppose",
      "category": "public-health",
      "level": "State",
      "impact": "High",
      "summary": "Relating to increasing the criminal penalty for the offense of assault committed against certain public servants and to the prosecution of the criminal offense of interference with public duties of those public servants.",
      "sponsor": "Bob Hall (R)",
      "lastAction": "",
      "lastActionDate": "",
      "actionCount": 0,
      "stoppedWithAction": false,
      "sourceUrl": "https://legiscan.com/TX/bill/SB1980/2025",
      "legiscan_bill_id": 1993326
    },
    {
      "billId": "TX-HB850",
      "state": "TX",
      "billNumber": "HB850",
      "title": "Relating to emergency cardiovascular care at public schools and certain private schools in this state.",
      "status": "Introduced",
      "isActive": "Yes",
      "billType": "anti",
      "stance": "Oppose",
      "category": "public-health",
      "level": "State",
      "impact": "Medium",
      "summary": "Relating to emergency cardiovascular care at public schools and certain private schools in this state.",
      "sponsor": "Suleman Lalani (D)",
      "lastAction": "",
      "lastActionDate": "",
      "actionCount": 0,
      "stoppedWithAction": false,
      "sourceUrl": "https://legiscan.com/TX/bill/HB850/2025",
      "legiscan_bill_id": 1890646
    },
    {
      "billId": "TX-HB121",
      "state": "TX",
      "billNumber": "HB121",
      "title": "Relating to measures for ensuring public school safety, including the commissioning of peace officers by the Texas Education Agency, the composition of the board of directors of the Texas School Safety Center, and public school safety and security requirements and resources.",
      "status": "Passed Both Chambers",
      "isActive": "Yes",
      "billType": "anti",
      "stance": "Oppose",
      "category": "vaccine-mandate",
      "level": "State",
      "impact": "High",
      "summary": "Relating to measures for ensuring public school safety, including the commissioning of peace officers by the Texas Education Agency, the composition of the board of directors of the Texas School Safety Center, and public school safety and security requirements and resources.",
      "sponsor": "Ken King (R)",
      "lastAction": "",
      "lastActionDate": "",
      "actionCount": 0,
      "stoppedWithAction": false,
      "sourceUrl": "https://legiscan.com/TX/bill/HB121/2025",
      "legiscan_bill_id": 2006342
    },
    {
      "billId": "TX-SB131",
      "state": "TX",
      "billNumber": "SB131",
      "title": "Relating to the enforcement within this state of certain federal laws for federally declared public health emergencies.",
      "status": "Introduced",
      "isActive": "Yes",
      "billType": "anti",
      "stance": "Oppose",
      "category": "public-health",
      "level": "State",
      "impact": "Medium",
      "summary": "Relating to the enforcement within this state of certain federal laws for federally declared public health emergencies.",
      "sponsor": "Bob Hall (R)",
      "lastAction": "",
      "lastActionDate": "",
      "actionCount": 0,
      "stoppedWithAction": false,
      "sourceUrl": "https://legiscan.com/TX/bill/SB131/2025",
      "legiscan_bill_id": 1891347
    },
    {
      "billId": "TX-HB1583",
      "state": "TX",
      "billNumber": "HB1583",
      "title": "Relating to the peace officer's notification of emergency detention form for persons evidencing mental illness and retention of that form.",
      "status": "In Committee",
      "isActive": "Yes",
      "billType": "anti",
      "stance": "Oppose",
      "category": "public-health",
      "level": "State",
      "impact": "High",
      "summary": "Relating to the peace officer's notification of emergency detention form for persons evidencing mental illness and retention of that form.",
      "sponsor": "Lacey Hull (R)",
      "lastAction": "",
      "lastActionDate": "",
      "actionCount": 0,
      "stoppedWithAction": false,
      "sourceUrl": "https://legiscan.com/TX/bill/HB1583/2025",
      "legiscan_bill_id": 1896012
    },
    {
      "billId": "TX-HB1306",
      "state": "TX",
      "billNumber": "HB1306",
      "title": "Relating to certain claims for benefits or compensation by a death investigation professional.",
      "status": "Passed Both Chambers",
      "isActive": "Yes",
      "billType": "anti",
      "stance": "Oppose",
      "category": "vaccine-liability",
      "level": "State",
      "impact": "High",
      "summary": "Relating to certain claims for benefits or compensation by a death investigation professional.",
      "sponsor": "Brooks Landgraf (R)",
      "lastAction": "",
      "lastActionDate": "",
      "actionCount": 0,
      "stoppedWithAction": false,
      "sourceUrl": "https://legiscan.com/TX/bill/HB1306/2025",
      "legiscan_bill_id": 1891929
    },
    {
      "billId": "TX-SB481",
      "state": "TX",
      "billNumber": "SB481",
      "title": "Relating to emergency preparedness and response plans for the continued care and safety of nursing facility and assisted living facility residents.",
      "status": "Introduced",
      "isActive": "Yes",
      "billType": "anti",
      "stance": "Oppose",
      "category": "public-health",
      "level": "State",
      "impact": "Medium",
      "summary": "Relating to emergency preparedness and response plans for the continued care and safety of nursing facility and assisted living facility residents.",
      "sponsor": "Carol Alvarado (D)",
      "lastAction": "",
      "lastActionDate": "",
      "actionCount": 0,
      "stoppedWithAction": false,
      "sourceUrl": "https://legiscan.com/TX/bill/SB481/2025",
      "legiscan_bill_id": 1893012
    },
    {
      "billId": "FL-H0917",
      "state": "FL",
      "billNumber": "H0917",
      "title": "Health Care",
      "status": "Introduced",
      "isActive": "Yes",
      "billType": "anti",
      "stance": "Oppose",
      "category": "vaccine-exemption",
      "level": "State",
      "impact": "High",
      "summary": "Defines \"treat,\" \"treated,\" & \"treatment\"; authorizes individual to refuse examination, testing, or treatment for specified reasons; prohibits discrimination against patient based on patient's vaccination status; requires licensed health care practitioners to inform parent or legal guardian of minor",
      "sponsor": "Jeff Holcomb (R)",
      "lastAction": "",
      "lastActionDate": "",
      "actionCount": 0,
      "stoppedWithAction": false,
      "sourceUrl": "https://legiscan.com/FL/bill/H0917/2026",
      "legiscan_bill_id": 2061091
    },
    {
      "billId": "FL-S0796",
      "state": "FL",
      "billNumber": "S0796",
      "title": "Veterinary Medicine",
      "status": "Introduced",
      "isActive": "Yes",
      "billType": "anti",
      "stance": "Oppose",
      "category": "vaccine-mandate",
      "level": "State",
      "impact": "Medium",
      "summary": "Citing this act as the \"Veterinary Workforce Innovation Act\"; increasing the amount of time for which prescriptions based solely on a veterinary telehealth evaluation may be issued for certain drugs; providing requirements for veterinary professional associates to receive certificates of registratio",
      "sponsor": "Rules",
      "lastAction": "",
      "lastActionDate": "",
      "actionCount": 0,
      "stoppedWithAction": false,
      "sourceUrl": "https://legiscan.com/FL/bill/S0796/2026",
      "legiscan_bill_id": 2057517
    },
    {
      "billId": "FL-H0339",
      "state": "FL",
      "billNumber": "H0339",
      "title": "Advertisement of a Harmful Vaccine",
      "status": "Introduced",
      "isActive": "Yes",
      "billType": "anti",
      "stance": "Oppose",
      "category": "vaccine-liability",
      "level": "State",
      "impact": "Medium",
      "summary": "Defines \"advertise\"; provides manufacturer liability; authorizes individual to file cause of action; provides that prevailing party is entitled to actual damages, court costs, & reasonable attorney fees.",
      "sponsor": "Civil Justice & Claims Subcommittee",
      "lastAction": "",
      "lastActionDate": "",
      "actionCount": 0,
      "stoppedWithAction": false,
      "sourceUrl": "https://legiscan.com/FL/bill/H0339/2026",
      "legiscan_bill_id": 2051585
    },
    {
      "billId": "FL-H0805",
      "state": "FL",
      "billNumber": "H0805",
      "title": "Veterinary Medicine",
      "status": "In Committee",
      "isActive": "Yes",
      "billType": "anti",
      "stance": "Oppose",
      "category": "vaccine-exemption",
      "level": "State",
      "impact": "High",
      "summary": "Defines \"veterinary professional associate\"; increases amount of time for which prescriptions based solely on veterinary telehealth evaluation may be issued for certain drugs; revises applicability of certain exemptions; provides requirements for veterinary professional associates to receive certifi",
      "sponsor": "Industries & Professional Activities Subcommittee",
      "lastAction": "",
      "lastActionDate": "",
      "actionCount": 0,
      "stoppedWithAction": false,
      "sourceUrl": "https://legiscan.com/FL/bill/H0805/2026",
      "legiscan_bill_id": 2059573
    },
    {
      "billId": "FL-S1382",
      "state": "FL",
      "billNumber": "S1382",
      "title": "Practice of Veterinary Medicine",
      "status": "Introduced",
      "isActive": "Yes",
      "billType": "anti",
      "stance": "Oppose",
      "category": "public-health",
      "level": "State",
      "impact": "Medium",
      "summary": "Revising the membership of the Board of Veterinary Medicine; specifying the services a veterinary technician or veterinary technologist must be licensed to perform, under the supervision of a licensed veterinarian; specifying that licensed veterinarians are responsible for all services performed by ",
      "sponsor": "Jonathan Martin (R)",
      "lastAction": "",
      "lastActionDate": "",
      "actionCount": 0,
      "stoppedWithAction": false,
      "sourceUrl": "https://legiscan.com/FL/bill/S1382/2026",
      "legiscan_bill_id": 2067717
    },
    {
      "billId": "FL-H0529",
      "state": "FL",
      "billNumber": "H0529",
      "title": "Community-based Care Lead Agency and Subcontractor Liability",
      "status": "Introduced",
      "isActive": "Yes",
      "billType": "anti",
      "stance": "Oppose",
      "category": "vaccine-mandate",
      "level": "State",
      "impact": "Medium",
      "summary": "Removes liability insurance coverage requirements for community-based care lead agencies; removes liability insurance coverage requirements for subcontractors of community-based care lead agencies; removes requirement to annually increase certain conditional limitations on damages by specified perce",
      "sponsor": "Judiciary Committee",
      "lastAction": "",
      "lastActionDate": "",
      "actionCount": 0,
      "stoppedWithAction": false,
      "sourceUrl": "https://legiscan.com/FL/bill/H0529/2026",
      "legiscan_bill_id": 2053981
    },
    {
      "billId": "FL-S1366",
      "state": "FL",
      "billNumber": "S1366",
      "title": "Claims Against the Government",
      "status": "Introduced",
      "isActive": "Yes",
      "billType": "anti",
      "stance": "Oppose",
      "category": "vaccine-liability",
      "level": "State",
      "impact": "Medium",
      "summary": "Increasing the statutory limits on the liability of the state and its agencies and subdivisions for tort claims; revising exceptions relating to instituting actions on tort claims against the state or one of its agencies or subdivisions; revising the period after which the failure of certain entitie",
      "sponsor": "Rules",
      "lastAction": "",
      "lastActionDate": "",
      "actionCount": 0,
      "stoppedWithAction": false,
      "sourceUrl": "https://legiscan.com/FL/bill/S1366/2026",
      "legiscan_bill_id": 2067462
    },
    {
      "billId": "FL-H0251",
      "state": "FL",
      "billNumber": "H0251",
      "title": "Pub. Rec./Emergency Department Physicians",
      "status": "Introduced",
      "isActive": "Yes",
      "billType": "anti",
      "stance": "Oppose",
      "category": "vaccine-exemption",
      "level": "State",
      "impact": "High",
      "summary": "Provides exemption from public records requirements for personal identifying & location information of current emergency department physicians & spouses & certain children of such emergency department physicians; provides for retroactive application; requires certain agencies that are custodians of ",
      "sponsor": "Health Professions & Programs Subcommittee",
      "lastAction": "",
      "lastActionDate": "",
      "actionCount": 0,
      "stoppedWithAction": false,
      "sourceUrl": "https://legiscan.com/FL/bill/H0251/2026",
      "legiscan_bill_id": 2047194
    },
    {
      "billId": "FL-H0457",
      "state": "FL",
      "billNumber": "H0457",
      "title": "Alternative Sources of Weather Information",
      "status": "Introduced",
      "isActive": "Yes",
      "billType": "anti",
      "stance": "Oppose",
      "category": "vaccine-mandate",
      "level": "State",
      "impact": "Medium",
      "summary": "Requires state comprehensive emergency plan evaluate integration of supplemental weather observational data & advanced forecasting products & effect on specified areas; defines \"advanced forecasting products\" & \"supplemental weather observational data\"; requires Division of Emergency Management to t",
      "sponsor": "Anne Gerwig (R)",
      "lastAction": "",
      "lastActionDate": "",
      "actionCount": 0,
      "stoppedWithAction": false,
      "sourceUrl": "https://legiscan.com/FL/bill/H0457/2026",
      "legiscan_bill_id": 2053079
    },
    {
      "billId": "FL-S0726",
      "state": "FL",
      "billNumber": "S0726",
      "title": "Alternative Sources of Weather Information",
      "status": "Introduced",
      "isActive": "Yes",
      "billType": "anti",
      "stance": "Oppose",
      "category": "vaccine-mandate",
      "level": "State",
      "impact": "Medium",
      "summary": "Revising the requirements of the state comprehensive emergency plan to include the evaluation of the integration of supplemental weather observational data and advanced forecasting products and the effects on specified areas; requiring the Division of Emergency Management to take specified actions t",
      "sponsor": "Stan McClain (R)",
      "lastAction": "",
      "lastActionDate": "",
      "actionCount": 0,
      "stoppedWithAction": false,
      "sourceUrl": "https://legiscan.com/FL/bill/S0726/2026",
      "legiscan_bill_id": 2056394
    },
    {
      "billId": "FL-H0355",
      "state": "FL",
      "billNumber": "H0355",
      "title": "Health Care Patient Protection",
      "status": "In Committee",
      "isActive": "Yes",
      "billType": "anti",
      "stance": "Oppose",
      "category": "vaccine-mandate",
      "level": "State",
      "impact": "High",
      "summary": "Requires hospital emergency departments to develop & implement policies & procedures, conduct training, record weights in certain manner, designate pediatric emergency care coordinator, & conduct specified assessments; authorizes hospital with emergency department to conduct National Pediatric Readi",
      "sponsor": "Health Care Facilities & Systems Subcommittee",
      "lastAction": "",
      "lastActionDate": "",
      "actionCount": 0,
      "stoppedWithAction": false,
      "sourceUrl": "https://legiscan.com/FL/bill/H0355/2026",
      "legiscan_bill_id": 2051662
    },
    {
      "billId": "FL-S0068",
      "state": "FL",
      "billNumber": "S0068",
      "title": "Health Care Patient Protection",
      "status": "Introduced",
      "isActive": "Yes",
      "billType": "anti",
      "stance": "Oppose",
      "category": "public-health",
      "level": "State",
      "impact": "Medium",
      "summary": "Requiring hospitals with emergency departments to develop and implement policies and procedures and conduct training; authorizing a hospital with an emergency department to conduct the National Pediatric Readiness Project's Open Assessment under certain circumstances; requiring the Agency for Health",
      "sponsor": "Appropriations Committee on Health and Human Services",
      "lastAction": "",
      "lastActionDate": "",
      "actionCount": 0,
      "stoppedWithAction": false,
      "sourceUrl": "https://legiscan.com/FL/bill/S0068/2026",
      "legiscan_bill_id": 2044896
    },
    {
      "billId": "FL-H0103",
      "state": "FL",
      "billNumber": "H0103",
      "title": "Local Business Taxes",
      "status": "In Committee",
      "isActive": "Yes",
      "billType": "anti",
      "stance": "Oppose",
      "category": "public-health",
      "level": "State",
      "impact": "High",
      "summary": "Repeals provisions related to local business taxes & authorizes certain local governments to continue to impose business taxes under specified conditions.",
      "sponsor": "State Affairs Committee",
      "lastAction": "",
      "lastActionDate": "",
      "actionCount": 0,
      "stoppedWithAction": false,
      "sourceUrl": "https://legiscan.com/FL/bill/H0103/2026",
      "legiscan_bill_id": 2045893
    },
    {
      "billId": "FL-H0733",
      "state": "FL",
      "billNumber": "H0733",
      "title": "Department of Health",
      "status": "In Committee",
      "isActive": "Yes",
      "billType": "anti",
      "stance": "Oppose",
      "category": "vaccine-mandate",
      "level": "State",
      "impact": "High",
      "summary": "Revises eligibility requirements for dental student loan repayment program; revises renewal period for certification of specified course; renaming compassionate use registry as medical marijuana registry; prohibits medical marijuana treatment center from being located within certain distance of spec",
      "sponsor": "Health & Human Services Committee",
      "lastAction": "",
      "lastActionDate": "",
      "actionCount": 0,
      "stoppedWithAction": false,
      "sourceUrl": "https://legiscan.com/FL/bill/H0733/2026",
      "legiscan_bill_id": 2058019
    },
    {
      "billId": "CA-AB144",
      "state": "CA",
      "billNumber": "AB144",
      "title": "Health.",
      "status": "Passed Both Chambers",
      "isActive": "Yes",
      "billType": "anti",
      "stance": "Oppose",
      "category": "public-health",
      "level": "State",
      "impact": "High",
      "summary": "An act to amend Sections 1246, 1300, 1300.1, 1625.6, 2473, 3041, and 3041.5 of, and to add Sections 901 and 4052.05 to, the Business and Professions Code, to amend Section 48980.4 of the Education Code, to amend Section 100520.5 of, and add Section 100503.6 to, the Government Code, to amend Sections",
      "sponsor": "Budget",
      "lastAction": "",
      "lastActionDate": "",
      "actionCount": 0,
      "stoppedWithAction": false,
      "sourceUrl": "https://legiscan.com/CA/bill/AB144/2025",
      "legiscan_bill_id": 1908129
    },
    {
      "billId": "CA-SB144",
      "state": "CA",
      "billNumber": "SB144",
      "title": "Health.",
      "status": "In Committee",
      "isActive": "Yes",
      "billType": "anti",
      "stance": "Oppose",
      "category": "public-health",
      "level": "State",
      "impact": "High",
      "summary": "An act to amend Sections 1246, 1300, 1300.1, 1625.6, 2473, 3041, and 3041.5 of, and to add Sections 901 and 4052.05 to, the Business and Professions Code, to amend Section 48980.4 of the Education Code, to amend Section 100520.5 of, and add Section 100503.6 to, the Government Code, to amend Sections",
      "sponsor": "Budget and Fiscal Review",
      "lastAction": "",
      "lastActionDate": "",
      "actionCount": 0,
      "stoppedWithAction": false,
      "sourceUrl": "https://legiscan.com/CA/bill/SB144/2025",
      "legiscan_bill_id": 1939241
    },
    {
      "billId": "CA-SB312",
      "state": "CA",
      "billNumber": "SB312",
      "title": "Dog importation: health certificates.",
      "status": "Passed Both Chambers",
      "isActive": "Yes",
      "billType": "anti",
      "stance": "Oppose",
      "category": "public-health",
      "level": "State",
      "impact": "High",
      "summary": "An act to add Chapter 4.5 (commencing with Section 31000) to Division 14 of the Food and Agricultural Code, and to repeal Chapter 1.5 (commencing with Section 121720) of Part 6 of Division 105 of the Health and Safety Code, relating to dogs.",
      "sponsor": "Tom Umberg (D)",
      "lastAction": "",
      "lastActionDate": "",
      "actionCount": 0,
      "stoppedWithAction": false,
      "sourceUrl": "https://legiscan.com/CA/bill/SB312/2025",
      "legiscan_bill_id": 1964732
    },
    {
      "billId": "CA-AB867",
      "state": "CA",
      "billNumber": "AB867",
      "title": "Veterinary medicine: cat declawing.",
      "status": "Passed Both Chambers",
      "isActive": "Yes",
      "billType": "anti",
      "stance": "Oppose",
      "category": "public-health",
      "level": "State",
      "impact": "High",
      "summary": "An act to amend Sections 4826, 4827, and 4883 of, and to add Section 4826.8 to, the Business and Professions Code, relating to healing arts.",
      "sponsor": "Alex Lee (D)",
      "lastAction": "",
      "lastActionDate": "",
      "actionCount": 0,
      "stoppedWithAction": false,
      "sourceUrl": "https://legiscan.com/CA/bill/AB867/2025",
      "legiscan_bill_id": 1976454
    },
    {
      "billId": "CA-SB290",
      "state": "CA",
      "billNumber": "SB290",
      "title": "CalWORKs.",
      "status": "In Committee",
      "isActive": "Yes",
      "billType": "anti",
      "stance": "Oppose",
      "category": "public-health",
      "level": "State",
      "impact": "High",
      "summary": "An act to amend, repeal, and add Section 11265.8 of the Welfare and Institutions Code, relating to CalWORKs.",
      "sponsor": "Lola Smallwood-Cuevas (D)",
      "lastAction": "",
      "lastActionDate": "",
      "actionCount": 0,
      "stoppedWithAction": false,
      "sourceUrl": "https://legiscan.com/CA/bill/SB290/2025",
      "legiscan_bill_id": 1961090
    },
    {
      "billId": "CA-AB961",
      "state": "CA",
      "billNumber": "AB961",
      "title": "Hazardous materials: California Land Reuse and Revitalization Act of 2004.",
      "status": "Passed Both Chambers",
      "isActive": "Yes",
      "billType": "anti",
      "stance": "Oppose",
      "category": "public-health",
      "level": "State",
      "impact": "High",
      "summary": "An act to amend Sections 25395.109 and 25395.110 of the Health and Safety Code, relating to hazardous materials.",
      "sponsor": "Anamarie Farias (D)",
      "lastAction": "",
      "lastActionDate": "",
      "actionCount": 0,
      "stoppedWithAction": false,
      "sourceUrl": "https://legiscan.com/CA/bill/AB961/2025",
      "legiscan_bill_id": 1978713
    },
    {
      "billId": "CA-SB747",
      "state": "CA",
      "billNumber": "SB747",
      "title": "Civil rights: deprivation of federal constitutional rights, privileges, and immunities.",
      "status": "In Committee",
      "isActive": "Yes",
      "billType": "anti",
      "stance": "Oppose",
      "category": "public-health",
      "level": "State",
      "impact": "High",
      "summary": "An act to add Section 53.8 to the Civil Code, relating to civil rights.",
      "sponsor": "Aisha Wahab (D)",
      "lastAction": "",
      "lastActionDate": "",
      "actionCount": 0,
      "stoppedWithAction": false,
      "sourceUrl": "https://legiscan.com/CA/bill/SB747/2025",
      "legiscan_bill_id": 1980477
    },
    {
      "billId": "CA-AB1074",
      "state": "CA",
      "billNumber": "AB1074",
      "title": "CalWORKs.",
      "status": "Vetoed",
      "isActive": "No",
      "billType": "anti",
      "stance": "Oppose",
      "category": "public-health",
      "level": "State",
      "impact": "High",
      "summary": "An act to amend Sections 11203 and 11325.21 of the Welfare and Institutions Code, relating to CalWORKs.",
      "sponsor": "Darshana Patel (D)",
      "lastAction": "",
      "lastActionDate": "",
      "actionCount": 0,
      "stoppedWithAction": false,
      "sourceUrl": "https://legiscan.com/CA/bill/AB1074/2025",
      "legiscan_bill_id": 1978609
    },
    {
      "billId": "CA-AB2651",
      "state": "CA",
      "billNumber": "AB2651",
      "title": "Informed Parents, Healthy Schools Act.",
      "status": "Introduced",
      "isActive": "Yes",
      "billType": "anti",
      "stance": "Oppose",
      "category": "public-health",
      "level": "State",
      "impact": "Medium",
      "summary": "An act to add Section 48986.5 to the Education Code, and to add Section 120141 to the Health and Safety Code, relating to immunizations.",
      "sponsor": "Mia Bonta (D)",
      "lastAction": "",
      "lastActionDate": "",
      "actionCount": 0,
      "stoppedWithAction": false,
      "sourceUrl": "https://legiscan.com/CA/bill/AB2651/2025",
      "legiscan_bill_id": 2121728
    },
    {
      "billId": "CA-ACR6",
      "state": "CA",
      "billNumber": "ACR6",
      "title": "Black April Memorial Month.",
      "status": "Passed Both Chambers",
      "isActive": "Yes",
      "billType": "anti",
      "stance": "Oppose",
      "category": "public-health",
      "level": "State",
      "impact": "High",
      "summary": "Relative to Black April Memorial Month.",
      "sponsor": "Ash Kalra (D)",
      "lastAction": "",
      "lastActionDate": "",
      "actionCount": 0,
      "stoppedWithAction": false,
      "sourceUrl": "https://legiscan.com/CA/bill/ACR6/2025",
      "legiscan_bill_id": 1896626
    },
    {
      "billId": "CA-AB45",
      "state": "CA",
      "billNumber": "AB45",
      "title": "Privacy: health data: location and research.",
      "status": "Passed Both Chambers",
      "isActive": "Yes",
      "billType": "anti",
      "stance": "Oppose",
      "category": "public-health",
      "level": "State",
      "impact": "High",
      "summary": "An act to amend Section 1798.99.90 of, to amend the heading of Title 1.81.49 (commencing with Section 1798.99.90) of Part 4 of Division 3 of, and to add Sections 1798.99.91, 1798.99.92, and 1798.99.93 to, the Civil Code, and to amend Section 140 of the Health and Safety Code, relating to privacy.",
      "sponsor": "Rebecca Bauer-Kahan (D)",
      "lastAction": "",
      "lastActionDate": "",
      "actionCount": 0,
      "stoppedWithAction": false,
      "sourceUrl": "https://legiscan.com/CA/bill/AB45/2025",
      "legiscan_bill_id": 1893383
    },
    {
      "billId": "CA-AB551",
      "state": "CA",
      "billNumber": "AB551",
      "title": "Reproductive Health Emergency Preparedness Program.",
      "status": "Signed into Law",
      "isActive": "No",
      "billType": "anti",
      "stance": "Oppose",
      "category": "public-health",
      "level": "State",
      "impact": "High",
      "summary": "An act to add and repeal Chapter 6.5 (commencing with Section 127650) of Part 2 of Division 107 of the Health and Safety Code, relating to health care.",
      "sponsor": "Maggy Krell (D)",
      "lastAction": "",
      "lastActionDate": "",
      "actionCount": 0,
      "stoppedWithAction": false,
      "sourceUrl": "https://legiscan.com/CA/bill/AB551/2025",
      "legiscan_bill_id": 1965865
    },
    {
      "billId": "CA-SB431",
      "state": "CA",
      "billNumber": "SB431",
      "title": "Assault and battery: utility workers.",
      "status": "In Committee",
      "isActive": "Yes",
      "billType": "anti",
      "stance": "Oppose",
      "category": "public-health",
      "level": "State",
      "impact": "High",
      "summary": "An act to amend Sections 241 and 243 of the Penal Code, relating to crimes.",
      "sponsor": "Jesse Arreguin (D)",
      "lastAction": "",
      "lastActionDate": "",
      "actionCount": 0,
      "stoppedWithAction": false,
      "sourceUrl": "https://legiscan.com/CA/bill/SB431/2025",
      "legiscan_bill_id": 1974541
    },
    {
      "billId": "CA-SB582",
      "state": "CA",
      "billNumber": "SB582",
      "title": "Health and care facilities: licensing during emergencies or disasters.",
      "status": "Passed Both Chambers",
      "isActive": "Yes",
      "billType": "anti",
      "stance": "Oppose",
      "category": "public-health",
      "level": "State",
      "impact": "High",
      "summary": "An act to amend Sections 1569.695 and 1596.8535 of, to add Sections 1418.23, 1524.2, 1524.3, 1568.069, 1568.257, 1569.192, and 1796.64 to, to add Chapter 7.6 (commencing with Section 11834.60) to Part 2 of Division 10.5 of, and to add Chapter 15 (commencing with Section 1796.80) to Division 2 of, th",
      "sponsor": "Henry Stern (D)",
      "lastAction": "",
      "lastActionDate": "",
      "actionCount": 0,
      "stoppedWithAction": false,
      "sourceUrl": "https://legiscan.com/CA/bill/SB582/2025",
      "legiscan_bill_id": 1978815
    },
    {
      "billId": "CA-SB568",
      "state": "CA",
      "billNumber": "SB568",
      "title": "Pupil health: epinephrine delivery systems: schoolsites and childcare programs.",
      "status": "Passed Both Chambers",
      "isActive": "Yes",
      "billType": "anti",
      "stance": "Oppose",
      "category": "public-health",
      "level": "State",
      "impact": "High",
      "summary": "An act to amend Section 4119.2 of the Business and Professions Code, and to amend Sections 49414 and 49423 of the Education Code, relating to pupil health.",
      "sponsor": "Roger Niello (R)",
      "lastAction": "",
      "lastActionDate": "",
      "actionCount": 0,
      "stoppedWithAction": false,
      "sourceUrl": "https://legiscan.com/CA/bill/SB568/2025",
      "legiscan_bill_id": 1978801
    },
    {
      "billId": "CA-AB546",
      "state": "CA",
      "billNumber": "AB546",
      "title": "Health care coverage: portable HEPA purifiers.",
      "status": "Vetoed",
      "isActive": "No",
      "billType": "anti",
      "stance": "Oppose",
      "category": "public-health",
      "level": "State",
      "impact": "High",
      "summary": "An act to add Section 1368.8 to the Health and Safety Code, and to add Section 10112.96 to the Insurance Code, relating to health care coverage, and declaring the urgency thereof, to take effect immediately.",
      "sponsor": "Jessica Caloza (D)",
      "lastAction": "",
      "lastActionDate": "",
      "actionCount": 0,
      "stoppedWithAction": false,
      "sourceUrl": "https://legiscan.com/CA/bill/AB546/2025",
      "legiscan_bill_id": 1965860
    },
    {
      "billId": "CA-SB340",
      "state": "CA",
      "billNumber": "SB340",
      "title": "General plans: housing element: emergency shelter.",
      "status": "Passed Both Chambers",
      "isActive": "Yes",
      "billType": "anti",
      "stance": "Oppose",
      "category": "public-health",
      "level": "State",
      "impact": "High",
      "summary": "An act to amend Section 65583 of the Government Code, and to amend Section 50801 of the Health and Safety Code, relating to housing.",
      "sponsor": "John Laird (D)",
      "lastAction": "",
      "lastActionDate": "",
      "actionCount": 0,
      "stoppedWithAction": false,
      "sourceUrl": "https://legiscan.com/CA/bill/SB340/2025",
      "legiscan_bill_id": 1968247
    },
    {
      "billId": "CA-AB1032",
      "state": "CA",
      "billNumber": "AB1032",
      "title": "Coverage for behavioral health visits.",
      "status": "Vetoed",
      "isActive": "No",
      "billType": "anti",
      "stance": "Oppose",
      "category": "public-health",
      "level": "State",
      "impact": "High",
      "summary": "An act to add Section 1368.9 to the Health and Safety Code, and to add Section 10112.97 to the Insurance Code, relating to health care coverage, and declaring the urgency thereof, to take effect immediately.",
      "sponsor": "John Harabedian (D)",
      "lastAction": "",
      "lastActionDate": "",
      "actionCount": 0,
      "stoppedWithAction": false,
      "sourceUrl": "https://legiscan.com/CA/bill/AB1032/2025",
      "legiscan_bill_id": 1978567
    },
    {
      "billId": "CA-AB306",
      "state": "CA",
      "billNumber": "AB306",
      "title": "Building regulations: state building standards.",
      "status": "In Committee",
      "isActive": "Yes",
      "billType": "anti",
      "stance": "Oppose",
      "category": "public-health",
      "level": "State",
      "impact": "High",
      "summary": "An act to amend Sections 17958, 17958.5, 17958.7, 18916, 18929.1, 18930, 18938.5, 18941.5, and 18942 of the Health and Safety Code, relating to building standards, and declaring the urgency thereof, to take effect immediately.",
      "sponsor": "Robert Rivas (D)",
      "lastAction": "",
      "lastActionDate": "",
      "actionCount": 0,
      "stoppedWithAction": false,
      "sourceUrl": "https://legiscan.com/CA/bill/AB306/2025",
      "legiscan_bill_id": 1939183
    }
  ]
}